{
	"info": {
		"_postman_id": "29add20b-0d8b-424a-bdd0-aa2e86d0cf08",
		"name": "musicLibrary",
		"schema": "https://schema.getpostman.com/json/collection/v2.1.0/collection.json"
	},
	"item": [
		{
			"name": "http://localhost:3000/api/music",
			"request": {
				"method": "GET",
				"header": [],
				"url": {
					"raw": "http://localhost:3000/api/music",
					"protocol": "http",
					"host": [
						"localhost"
					],
					"port": "3000",
					"path": [
						"api",
						"music"
					]
				}
			},
			"response": []
		}
	]
}